galpynostatic/__init__.py
galpynostatic/base.py
galpynostatic/make_prediction.py
galpynostatic/metric.py
galpynostatic/model.py
galpynostatic/plot.py
galpynostatic/preprocessing.py
galpynostatic/utils.py
galpynostatic/datasets/__init__.py
galpynostatic/datasets/cylindrical.csv
galpynostatic/datasets/planar.csv
galpynostatic/datasets/spherical.csv
galpynostatic-0.4.1.dist-info/LICENSE
galpynostatic-0.4.1.dist-info/METADATA
galpynostatic-0.4.1.dist-info/WHEEL
galpynostatic-0.4.1.dist-info/top_level.txt
galpynostatic-0.4.1.dist-info/RECORD
