Metadata-Version: 2.1
Name: galpynostatic
Version: 0.4.1
Summary: A Python package with physics-based models to predict optimal conditions for fast-charging lithium-ion batteries.
Author-email: Francisco Fernandez <ffernandev@gmail.com>
License: MIT License
Project-URL: Homepage, https://github.com/fernandezfran/galpynostatic
Keywords: battery,physics-based,data-driven,heuristic-algorithm,regression-models
Classifier: Development Status :: 4 - Beta
Classifier: Intended Audience :: Science/Research
Classifier: Operating System :: OS Independent
Classifier: Programming Language :: Python
Classifier: Programming Language :: Python :: 3.9
Classifier: Programming Language :: Python :: 3.10
Classifier: Programming Language :: Python :: 3.11
Classifier: Programming Language :: Python :: 3.12
Classifier: Topic :: Scientific/Engineering
License-File: LICENSE
Requires-Dist: importlib-metadata
Requires-Dist: matplotlib
Requires-Dist: numpy
Requires-Dist: pandas
Requires-Dist: scikit-learn
Requires-Dist: scipy
